[
  {
    "id": "lIlf9FfOu1Gqf0RAkapS",
    "name": "मातृ मृत्यु"
  },
  {
    "id": "odZQBYEZ03d3WafaQt1x",
    "name": "नवजात"
  },
  {
    "id": "hGnfyrpwcjadJC1woppB",
    "name": "नवजात, मातृ मृत्यु"
  },
  {
    "id": "LYw1L3Y5UhOoXeqTnvtv",
    "name": "गर्भावस्था के दौरान देखभाल"
  },
  {
    "id": "Xzs6rRQxXRwVPa9yr351",
    "name": "परामर्श/कौन्सिलिंग"
  },
  {
    "id": "EJt6kXtSg0VNFzOXytZS",
    "name": "एलएमपी"
  },
  {
    "id": "UiHMFqXa122vU1OhcyVA",
    "name": "स्तनपान"
  },
  {
    "id": "R9HoW8nH8KoTAYN2ALzY",
    "name": "पोषण"
  },
  {
    "id": "gP1VJDNJE82oqWoFoyLY",
    "name": "विशेष जरूरतों वाली महिलाएँ"
  },
  {
    "id": "w3fgZ0Cz2WqAnwGyGEXS",
    "name": " परामर्श/कौन्सिलिंग"
  },
  {
    "id": "mwQy9gv9x5IIS6AcNa6z",
    "name": "हिंसा की शिकार महिलाएँ"
  },
  {
    "id": "sGkkn5bgWefcrPZCgT2f",
    "name": "हाथ की स्वच्छता"
  },
  {
    "id": "Au4RizFufArxW7Qli7xp",
    "name": "त्वचा की अविभाज्यता"
  },
  {
    "id": "mjd29AQUSPjBUKqv0JG4",
    "name": "मधुमेह, संक्रमण"
  },
  {
    "id": "DgM7MCfkIaHjTuJu4VZM",
    "name": "घरेलू अपशिष्ट"
  },
  {
    "id": "nFq0WKYpOgzq5cHEyr8T",
    "name": "माहवारी"
  },
  {
    "id": "tmWOZZHHWdyao8RtOHTa",
    "name": "क्षय रोग या टीबी"
  },
  {
    "id": "czjjHIrFqc0XC6q1oymM",
    "name": "गैर संचारित रोग, उच्च रक्तचाप"
  },
  {
    "id": "23wXjVN8BZr4A9Cu0LCa",
    "name": "गैर संचारित रोग, दिल की बिमारियाँ"
  },
  {
    "id": "uHznLsEItHzwvH8iuGmz",
    "name": "गैर संचारित रोग"
  },
  {
    "id": "qVeliCyotTCO3PsPnwrp",
    "name": "मधुमेह"
  },
  {
    "id": "QIIJB1uhbEUDpaXv1xxf",
    "name": "कैंसर"
  },
  {
    "id": "iEMFOyjezjRekOEhC465",
    "name": "योनि-ग्रीवा का कैंसर"
  },
  {
    "id": "mqPXb2kpgZ3qaVdInc4w",
    "name": "स्तन कैंसर"
  },
  {
    "id": "ZxJZM1480LefM96ni4Qw",
    "name": "मुँह के कैंसर"
  }
]
